{
    "key": "group_5f553b6287def",
    "title": "Page Options",
    "fields": [
        {
            "key": "field_5f553b6a5cae3",
            "label": "Page type",
            "name": "page_type",
            "type": "select",
            "instructions": "",
            "required": 1,
            "conditional_logic": 0,
            "wrapper": {
                "width": "",
                "class": "",
                "id": ""
            },
            "show_in_graphql": 1,
            "choices": {
                "general": "General Page",
                "login": "Login Page",
                "register": "Register Page",
                "logout": "Logout Page",
                "user_account": "User Account Page"
            },
            "default_value": "general",
            "allow_null": 0,
            "multiple": 0,
            "ui": 1,
            "ajax": 0,
            "return_format": "value",
            "placeholder": ""
        },
        {
            "key": "field_5f8a5ef578314",
            "label": "Page Scripts",
            "name": "",
            "type": "tab",
            "instructions": "",
            "required": 0,
            "conditional_logic": 0,
            "wrapper": {
                "width": "",
                "class": "",
                "id": ""
            },
            "show_in_graphql": 1,
            "placement": "top",
            "endpoint": 0
        },
        {
            "key": "field_5f8a5f3278317",
            "label": "Header Scripts Override",
            "name": "header_scripts_override",
            "type": "true_false",
            "instructions": "",
            "required": 0,
            "conditional_logic": [
                [
                    {
                        "field": "field_5f553b6a5cae3",
                        "operator": "!=empty"
                    }
                ]
            ],
            "wrapper": {
                "width": "20",
                "class": "",
                "id": ""
            },
            "show_in_graphql": 1,
            "message": "",
            "default_value": 0,
            "ui": 1,
            "ui_on_text": "",
            "ui_off_text": ""
        },
        {
            "key": "field_5f8a5f0a78315",
            "label": "Header Scripts",
            "name": "header_scripts",
            "type": "textarea",
            "instructions": "",
            "required": 0,
            "conditional_logic": 0,
            "wrapper": {
                "width": "80",
                "class": "",
                "id": ""
            },
            "show_in_graphql": 1,
            "default_value": "",
            "placeholder": "",
            "maxlength": "",
            "rows": "",
            "new_lines": ""
        },
        {
            "key": "field_5f8a5f7078318",
            "label": "Footer Scripts Override",
            "name": "footer_scripts_override",
            "type": "true_false",
            "instructions": "",
            "required": 0,
            "conditional_logic": [
                [
                    {
                        "field": "field_5f553b6a5cae3",
                        "operator": "!=empty"
                    }
                ]
            ],
            "wrapper": {
                "width": "20",
                "class": "",
                "id": ""
            },
            "show_in_graphql": 1,
            "message": "",
            "default_value": 0,
            "ui": 1,
            "ui_on_text": "",
            "ui_off_text": ""
        },
        {
            "key": "field_5f8a5f2078316",
            "label": "Footer Scripts",
            "name": "footer_scripts",
            "type": "textarea",
            "instructions": "",
            "required": 0,
            "conditional_logic": 0,
            "wrapper": {
                "width": "80",
                "class": "",
                "id": ""
            },
            "show_in_graphql": 1,
            "default_value": "",
            "placeholder": "",
            "maxlength": "",
            "rows": "",
            "new_lines": ""
        }
    ],
    "location": [
        [
            {
                "param": "post_type",
                "operator": "==",
                "value": "page"
            }
        ],
        [
            {
                "param": "post_type",
                "operator": "==",
                "value": "item_view_templates"
            }
        ]
    ],
    "menu_order": 0,
    "position": "normal",
    "style": "default",
    "label_placement": "top",
    "instruction_placement": "label",
    "hide_on_screen": "",
    "active": true,
    "description": "",
    "show_in_graphql": 1,
    "graphql_field_name": "page_options",
    "modified": 1602933963
}